{
  "indexes": [
    {
      "collectionGroup": "posts",
      "queryScope": "COLLECTION",
      "fields": [
        {
          "fieldPath": "categories",
          "arrayConfig": "CONTAINS"
        },
        {
          "fieldPath": "createdAt",
          "order": "DESCENDING"
        },
        {
          "fieldPath": "__name__",
          "order": "DESCENDING"
        }
      ],
      "density": "SPARSE_ALL"
    },
    {
      "collectionGroup": "Users",
      "queryScope": "COLLECTION",
      "fields": [
        {
          "fieldPath": "categories",
          "order": "ASCENDING"
        },
        {
          "fieldPath": "uid",
          "order": "ASCENDING"
        },
        {
          "fieldPath": "__name__",
          "order": "ASCENDING"
        }
      ],
      "density": "SPARSE_ALL"
    }
  ],
  "fieldOverrides": []
}